mag_tools/__init__.py
mag_tools/__pycache__/__init__.cpython-313.pyc
mag_tools/bean/__init__.py
mag_tools/bean/array.py
mag_tools/bean/base_data.py
mag_tools/bean/data_format.py
mag_tools/bean/db_list.py
mag_tools/bean/db_page.py
mag_tools/bean/dimension.py
mag_tools/bean/easy_map.py
mag_tools/bean/kv_pair.py
mag_tools/bean/result.py
mag_tools/bean/results.py
mag_tools/bean/text_format.py
mag_tools/bean/usb_device.py
mag_tools/bean/common/__init__.py
mag_tools/bean/common/base_data.py
mag_tools/bean/common/base_test.py
mag_tools/bean/common/data_format.py
mag_tools/bean/common/test_result.py
mag_tools/bean/common/text_format.py
mag_tools/bean/sys/__init__.py
mag_tools/bean/sys/computer.py
mag_tools/bean/sys/cpu.py
mag_tools/bean/sys/disk.py
mag_tools/bean/sys/disk_partition.py
mag_tools/bean/sys/memory.py
mag_tools/bean/sys/memory_module.py
mag_tools/bean/sys/mother_board.py
mag_tools/bean/sys/operate_system.py
mag_tools/bean/sys/usb_device.py
mag_tools/config/__init__.py
mag_tools/config/config.py
mag_tools/config/sys_config.py
mag_tools/core/__init__.py
mag_tools/core/service_lifecycle.py
mag_tools/db/__init__.py
mag_tools/db/datasource.py
mag_tools/db/datasource_info.py
mag_tools/enums/__init__.py
mag_tools/enums/base_enum.py
mag_tools/enums/client_type.py
mag_tools/enums/computer_type.py
mag_tools/enums/convert_type.py
mag_tools/enums/cpu_series.py
mag_tools/enums/crypt_alg.py
mag_tools/enums/digest_alg.py
mag_tools/enums/fs_type.py
mag_tools/enums/justify_type.py
mag_tools/enums/log_type.py
mag_tools/enums/masking_alg.py
mag_tools/enums/media_type.py
mag_tools/enums/memory_type.py
mag_tools/enums/message_type.py
mag_tools/enums/process_status.py
mag_tools/enums/service_status.py
mag_tools/enums/symbol.py
mag_tools/enums/time_unit.py
mag_tools/enums/usb_type.py
mag_tools/enums/user_type.py
mag_tools/exception/__init__.py
mag_tools/exception/app_exception.py
mag_tools/exception/dao_exception.py
mag_tools/format/__init__.py
mag_tools/format/string_format.py
mag_tools-0.3.142.dist-info/METADATA
mag_tools-0.3.142.dist-info/WHEEL
mag_tools-0.3.142.dist-info/top_level.txt
mag_tools-0.3.142.dist-info/RECORD
