Metadata-Version: 2.4
Name: mag_tools
Version: 0.3.142
Summary: 常用工具包
Home-page: http://gitlab.magnetitech.com:8088/sources/frame/py-frame/mag_tools.git
Author: xlcao
Author-email: xl_cao@hotmail.com
Classifier: Programming Language :: Python :: 3
Classifier: License :: OSI Approved :: MIT License
Classifier: Operating System :: OS Independent
Requires-Python: >=3.6
Dynamic: author
Dynamic: author-email
Dynamic: classifier
Dynamic: description
Dynamic: description-content-type
Dynamic: home-page
Dynamic: requires-python
Dynamic: summary
